LICENSE
MANIFEST.in
README.md
anusah.py
setup.py
anusah.egg-info/PKG-INFO
anusah.egg-info/SOURCES.txt
anusah.egg-info/dependency_links.txt
anusah.egg-info/entry_points.txt
anusah.egg-info/requires.txt
anusah.egg-info/top_level.txt
app/__init__.py
app/__main__.py
app/application.py