Metadata-Version: 2.1
Name: anusah
Version: 0.0.1
Summary: Generic CLI tool anusah
Home-page: UNKNOWN
Author: Anurag Goenka, Ashutosh Sah
Author-email: anurag.goenka25@gmail.com
License: MIT
Platform: UNKNOWN
Classifier: Programming Language :: Python :: 3.9
Classifier: License :: OSI Approved :: MIT License
Classifier: Operating System :: OS Independent
Requires-Python: >=3.7
License-File: LICENSE
